{
    "songs": [
	   {
            "name": "Gods Plan",
        },
	   {
            "name": "Be Careful",
        },
	   {
            "name": "Look Alive",
        },
	   {
            "name": "Apna Time Aayega",
        },
	   {
            "name": "O SAKI SAKI",
        },
	   {
            "name": "Khalibali",
        },
	   {
            "name": "Dhadak Title Track",
        },
        {
            "name": "Bom Diggy",
        },
        {
            "name": "In My Feelings",
        },
        {
            "name": "No Tears Left to Cry",  
        },
	   {
            "name": "Rockstar", 
        },{
            "name": "Shallow", 
        },{
            "name": "Perfect",
        },{
		    "name": "Love Yourself",
        },
		{
		    "name": "Sugar",
        },
		{
		    "name": "Wake Me Up",
        },
		{
		    "name": "Bili Jn",
        },
		{
		    "name": "Mere Humsafar",
        },
		{
		    "name": "Tere Bin",
        },
		{
		    "name": "Sun Raha He",
        },
		{
		    "name": "Rabta",
        },
		{
		    "name": "Dil He Dil",
        },
		{
		    "name": "Utwn",
        },
		{
		    "name": "Good For You",
        },
		{
		    "name": "Sl Dn",
        },
		{
		    "name": "Wh Sys",
        },
		{
		    "name": "Evertime",
        },
		{
		    "name": "Lucky",
        },
		{
		    "name": "Tmh kya Samjte He",
        },
		{
		    "name": "Yeh Mera Dil",
        },
		{
		    "name": "Teri Or",
        }
  ]
}
